int2str/__init__.py
int2str/converter.py
num_management/__init__.py
num_management/converter.py
num_management-1.0.dist-info/METADATA
num_management-1.0.dist-info/WHEEL
num_management-1.0.dist-info/top_level.txt
num_management-1.0.dist-info/RECORD
