Metadata-Version: 2.1
Name: num-management
Version: 1.0
Summary: This Library is used for manage numbers with different methods. Method int2str is included in this library.
Home-page: https://bitbucket.org/onprem/olvera_carlos_interview-numbertostring-python/src/caor_int_to_string/
Author: Carlos Alberto Olvera Rodriguez
Author-email: orcas40@gmail.com
License: MIT
Classifier: Programming Language :: Python :: 3
Classifier: License :: OSI Approved :: MIT License
Classifier: Operating System :: OS Independent
Requires-Python: >=3.6
